us_pls/__init__.py
us_pls/_client.py
us_pls/_config.py
us_pls/_download/__init__.py
us_pls/_download/download_service.py
us_pls/_download/interface.py
us_pls/_download/models.py
us_pls/_logger/__init__.py
us_pls/_logger/configure_logger.py
us_pls/_logger/factory.py
us_pls/_logger/filters.py
us_pls/_logger/interface.py
us_pls/_persistence/__init__.py
us_pls/_persistence/interface.py
us_pls/_persistence/on_disk_cache.py
us_pls/_scraper/__init__.py
us_pls/_scraper/interface.py
us_pls/_scraper/scraping_service.py
us_pls/_stats/__init__.py
us_pls/_stats/interface.py
us_pls/_stats/stats_service.py
us_pls/_transformer/__init__.py
us_pls/_transformer/interface.py
us_pls/_transformer/transformation_service.py
us_pls/_variables/__init__.py
us_pls/_variables/_data_dicts.py
us_pls/_variables/fy2018/__init__.py
us_pls/_variables/fy2018/outlet_data_vars.py
us_pls/_variables/fy2018/state_summary_data_vars.py
us_pls/_variables/fy2018/system_data_vars.py
us_pls/_variables/interface.py
us_pls/_variables/models.py
us_pls/_variables/repository.py
us_pls/libraries.py
us_pls-0.0.2a7.dist-info/LICENSE
us_pls-0.0.2a7.dist-info/WHEEL
us_pls-0.0.2a7.dist-info/METADATA
us_pls-0.0.2a7.dist-info/RECORD
