Metadata-Version: 2.1
Name: us-pls
Version: 0.0.2a7
Summary: Client to get and analyze data from the US Public Library Survey
Home-page: https://github.com/drawjk705/us-libraries
License: MIT
Author: Joel Krim
Author-email: drawjk705@gmail.com
Requires-Python: >=3.9,<4.0
Classifier: License :: OSI Approved :: MIT License
Classifier: Programming Language :: Python :: 3
Classifier: Programming Language :: Python :: 3.9
Requires-Dist: beautifulsoup4 (>=4.9.3,<5.0.0)
Requires-Dist: pandas (>=1.2.1,<2.0.0)
Requires-Dist: punq (>=0.4.1,<0.5.0)
Requires-Dist: requests (>=2.25.1,<3.0.0)
Project-URL: Repository, https://github.com/drawjk705/us-libraries
